trashit/__init__.py
trashit/command_line.py
trashit/trashcommands.py
trashit/trashlib.py
trashit-1.5.1.dist-info/LICENSE
trashit-1.5.1.dist-info/METADATA
trashit-1.5.1.dist-info/WHEEL
trashit-1.5.1.dist-info/entry_points.txt
trashit-1.5.1.dist-info/top_level.txt
trashit-1.5.1.dist-info/RECORD
