Metadata-Version: 2.1
Name: trashit
Version: 1.5.1
Summary: A Python-built package for sending files or folders to Trash.
Home-page: https://github.com/Shreyas-Ashtamkar/Trash-CLI
Author: Shreyas Ashtamkar
Author-email: shreyu@programmer.net
License: MIT
Platform: UNKNOWN
Classifier: Programming Language :: Python :: 3
Classifier: Programming Language :: Python :: 3.6
Classifier: Programming Language :: Python :: 3.7
Classifier: Programming Language :: Python :: 3.8
Classifier: License :: OSI Approved :: MIT License
Classifier: Operating System :: POSIX :: Linux
Requires-Python: >=3.6
Requires-Dist: colorama
